OSCR/__init__.py
OSCR/cli.py
OSCR/combat.py
OSCR/constants.py
OSCR/datamodels.py
OSCR/detection.py
OSCR/iofunc.py
OSCR/liveparser.py
OSCR/main.py
OSCR/oscr_read_file_backwards.py
OSCR/parser.py
OSCR/utilities.py
sto_oscr-2025.8.10.0.dist-info/METADATA
sto_oscr-2025.8.10.0.dist-info/WHEEL
sto_oscr-2025.8.10.0.dist-info/entry_points.txt
sto_oscr-2025.8.10.0.dist-info/licenses/LICENSE
sto_oscr-2025.8.10.0.dist-info/RECORD
