Metadata-Version: 2.4
Name: STO-OSCR
Version: 2025.8.10.0
Summary: Open Source Combatlog Reader for Star Trek Online.
Project-URL: Homepage, https://github.com/STOCD/OSCR
Project-URL: Repository, https://github.com/STOCD/OSCR.git
Project-URL: Bug Tracker, https://github.com/STOCD/OSCR/issues
License:                     GNU GENERAL PUBLIC LICENSE
License-File: LICENSE
Classifier: Development Status :: 4 - Beta
Classifier: Programming Language :: Python
Requires-Python: >=3.9
Requires-Dist: numpy>=1.26.1
Provides-Extra: cli
Provides-Extra: gui
